cli/__init__.py
cli/setup.py
cli/rebrickable_cli/__init__.py
cli/rebrickable_cli/utils.py
cli/rebrickable_cli/cli/__init__.py
cli/rebrickable_cli/cli/common.py
cli/rebrickable_cli/cli/lego.py
cli/rebrickable_cli/cli/main.py
cli/rebrickable_cli/cli/user.py
cli/rebrickable_cli/cli/users.py
data/__init__.py
data/setup.py
data/rebrickable_data/__init__.py
data/rebrickable_data/cli.py
data/rebrickable_data/database.py
data/rebrickable_data/download.py
data/rebrickable_data/importing.py
data/rebrickable_data/utils.py
data/rebrickable_data/models/__init__.py
data/rebrickable_data/models/colors.py
data/rebrickable_data/models/inventories.py
data/rebrickable_data/models/parts.py
data/rebrickable_data/models/sets.py
data/rebrickable_data/models/themes.py
pyrebrickable_cli-0.8.0.dist-info/DESCRIPTION.rst
pyrebrickable_cli-0.8.0.dist-info/METADATA
pyrebrickable_cli-0.8.0.dist-info/RECORD
pyrebrickable_cli-0.8.0.dist-info/WHEEL
pyrebrickable_cli-0.8.0.dist-info/entry_points.txt
pyrebrickable_cli-0.8.0.dist-info/metadata.json
pyrebrickable_cli-0.8.0.dist-info/top_level.txt
tests/__init__.py
tests/conftest.py
tests/utils.py
tests/cli/__init__.py
tests/cli/test_lego.py
tests/cli/test_main.py
tests/cli/test_models_integration.py
tests/cli/test_user.py
tests/cli/test_users.py
tests/cli/test_utils.py
tests/data/__init__.py
tests/data/tests_data.py
