Metadata-Version: 2.0
Name: pyrebrickable-cli
Version: 0.8.0
Summary: This is rebrickable_cli, providing a CLI python wrapper around the Rebrickable API
Requires-Dist: pyrebrickable-api
Requires-Dist: appdirs
Requires-Dist: enum34
Requires-Dist: PyYaml
Requires-Dist: click (>=6)
